termind/__init__.py
termind/cli.py
termind/config.py
termind/conversation.py
termind/models.py
termind-0.1.0.dist-info/LICENSE
termind-0.1.0.dist-info/METADATA
termind-0.1.0.dist-info/WHEEL
termind-0.1.0.dist-info/entry_points.txt
termind-0.1.0.dist-info/top_level.txt
termind-0.1.0.dist-info/RECORD
