Metadata-Version: 2.1
Name: termind
Version: 0.1.0
Summary: A command-line AI chat tool for testing various large model APIs
Home-page: https://github.com/luhuadong/termind
Author: luhuadong
Author-email: luhuadong@163.com
Classifier: Development Status :: 3 - Alpha
Classifier: Intended Audience :: Developers
Classifier: License :: OSI Approved :: MIT License
Classifier: Programming Language :: Python :: 3
Classifier: Programming Language :: Python :: 3.7
Classifier: Programming Language :: Python :: 3.8
Classifier: Programming Language :: Python :: 3.9
Classifier: Programming Language :: Python :: 3.10
Requires-Python: >=3.7
License-File: LICENSE
Requires-Dist: openai >=0.27.0
Requires-Dist: requests >=2.26.0
Requires-Dist: rich >=12.4.0
Requires-Dist: python-dotenv >=0.19.0
